dolfin_warp/Energy.py
dolfin_warp/Energy_Continuous.py
dolfin_warp/Energy_Continuous_Constraint.py
dolfin_warp/Energy_Continuous_GeneratedImage.py
dolfin_warp/Energy_Continuous_Regularization.py
dolfin_warp/Energy_Continuous_WarpedImage.py
dolfin_warp/Energy_Discrete.py
dolfin_warp/Energy_Discrete_SimpleRegularization.py
dolfin_warp/Energy_Discrete_SurfaceRegularization.py
dolfin_warp/Energy_Discrete_VolumeRegularization.py
dolfin_warp/FilesSeries.py
dolfin_warp/FilesSeries_Images.py
dolfin_warp/FilesSeries_Meshes.py
dolfin_warp/ImageIterator.py
dolfin_warp/ModalAnalysis.py
dolfin_warp/NonlinearSolver.py
dolfin_warp/NonlinearSolver_CMA.py
dolfin_warp/NonlinearSolver_Newton.py
dolfin_warp/NonlinearSolver_Relaxation.py
dolfin_warp/Problem.py
dolfin_warp/Problem_FullKinematicsWarping.py
dolfin_warp/Problem_ReducedKinematicsWarping.py
dolfin_warp/Problem_Warping.py
dolfin_warp/__init__.py
dolfin_warp/compute_best_regularization_strength.py
dolfin_warp/compute_displacement_error.py
dolfin_warp/compute_displacement_error_field.py
dolfin_warp/compute_displacement_infinity_norm.py
dolfin_warp/compute_displacements_from_ref.py
dolfin_warp/compute_downsampled_images.py
dolfin_warp/compute_energies_normalization.py
dolfin_warp/compute_equalized_images.py
dolfin_warp/compute_normalized_images.py
dolfin_warp/compute_projected_image.py
dolfin_warp/compute_quadrature_degree.py
dolfin_warp/compute_regularization_energies.py
dolfin_warp/compute_selective_image_gradient.py
dolfin_warp/compute_strain_error.py
dolfin_warp/compute_strains.py
dolfin_warp/compute_unwarped_images.py
dolfin_warp/compute_warped_images.py
dolfin_warp/compute_warped_mesh.py
dolfin_warp/expressions_char_func_cpp.py
dolfin_warp/expressions_generated_images_cpp.py
dolfin_warp/expressions_images_cpp.py
dolfin_warp/expressions_images_py.py
dolfin_warp/expressions_static_scaling_cpp.py
dolfin_warp/generate_images.py
dolfin_warp/generate_images_Image.py
dolfin_warp/generate_images_Mapping.py
dolfin_warp-2025.4.17.dist-info/licenses/LICENSE
dolfin_warp-2025.4.17.dist-info/METADATA
dolfin_warp-2025.4.17.dist-info/WHEEL
dolfin_warp-2025.4.17.dist-info/top_level.txt
dolfin_warp-2025.4.17.dist-info/RECORD
