Metadata-Version: 2.4
Name: dolfin_warp
Version: 2025.4.17
Summary: [![PyPi Version](https://img.shields.io/pypi/v/dolfin-warp.svg?style=flat-square)](https://pypi.org/project/dolfin-warp)
Home-page: https://github.com/mgenet/dolfin_warp
Author: Martin Genet
Author-email: martin.genet@polytechnique.edu
License: GPLv3
Classifier: Programming Language :: Python :: 3
Classifier: License :: OSI Approved :: GNU General Public License v3 (GPLv3)
Classifier: Operating System :: OS Independent
License-File: LICENSE
Requires-Dist: gnuplot
Requires-Dist: matplotlib
Requires-Dist: meshio
Requires-Dist: numpy
Requires-Dist: pandas
Requires-Dist: scipy
Requires-Dist: vtk
Requires-Dist: myPythonLibrary
Requires-Dist: myVTKPythonLibrary
Requires-Dist: vtkpython_cbl
Requires-Dist: dolfin_mech
Dynamic: author
Dynamic: author-email
Dynamic: classifier
Dynamic: description
Dynamic: description-content-type
Dynamic: home-page
Dynamic: license
Dynamic: license-file
Dynamic: requires-dist
Dynamic: summary
